{
	"class" : {
		"context:constructor:" : "jf 7/19/2009 14:10" },
	"instance" : {
		"add:" : "lr 1/14/2010 19:06",
		"add:context:" : "lr 1/14/2010 19:06",
		"addBack" : "JohanBrichau 2/23/2014 00:01",
		"addClass:" : "lr 1/14/2010 19:07",
		"after:" : "lr 1/14/2010 19:08",
		"andSelf" : "JohanBrichau 2/23/2014 00:38",
		"animate" : "lr 1/14/2010 19:10",
		"append:" : "lr 1/14/2010 19:10",
		"appendTo:" : "lr 1/14/2010 19:10",
		"at:" : "lr 9/13/2009 10:47",
		"atAll" : "lr 9/13/2009 10:47",
		"attributeAt:" : "lr 1/14/2010 19:11",
		"attributeAt:put:" : "lr 1/14/2010 19:11",
		"attributes:" : "lr 1/14/2010 19:11",
		"before:" : "lr 1/14/2010 19:11",
		"bind:data:do:" : "lr 10/17/2010 17:46",
		"bind:do:" : "lr 1/14/2010 19:31",
		"children" : "lr 1/14/2010 19:14",
		"children:" : "lr 1/14/2010 19:14",
		"clearQueue" : "lr 1/14/2010 19:15",
		"clearQueue:" : "lr 1/14/2010 19:15",
		"clone" : "lr 1/14/2010 19:16",
		"cloneAll" : "lr 1/14/2010 19:16",
		"closest" : "lr 1/14/2010 19:17",
		"closest:" : "lr 1/14/2010 19:17",
		"collect:" : "lr 1/25/2010 22:07",
		"contents" : "lr 1/14/2010 19:17",
		"context" : "lr 1/14/2010 19:17",
		"css:" : "lr 1/14/2010 19:18",
		"cssAt:" : "lr 1/14/2010 19:17",
		"cssAt:put:" : "lr 1/14/2010 19:18",
		"dataAt:" : "lr 10/17/2010 17:50",
		"dataAt:put:" : "lr 1/14/2010 19:18",
		"delay:" : "lr 1/14/2010 19:19",
		"delay:queue:" : "lr 1/14/2010 19:19",
		"delegate:on:data:do:" : "lr 2/20/2010 18:10",
		"delegate:on:do:" : "lr 2/20/2010 18:10",
		"dequeue" : "lr 1/14/2010 19:19",
		"dequeue:" : "lr 1/14/2010 19:19",
		"detach" : "lr 1/14/2010 19:20",
		"detach:" : "lr 1/14/2010 19:20",
		"do:" : "lr 1/14/2010 21:34",
		"each:" : "lr 1/14/2010 21:34",
		"empty" : "lr 1/14/2010 19:21",
		"end" : "lr 1/14/2010 19:21",
		"eq:" : "lr 1/14/2010 19:21",
		"fade:to:" : "lr 1/14/2010 19:22",
		"fade:to:callback:" : "lr 1/14/2010 19:22",
		"fadeIn:" : "lr 1/14/2010 19:22",
		"fadeIn:callback:" : "lr 1/14/2010 19:22",
		"fadeOut:" : "lr 1/14/2010 19:22",
		"fadeOut:callback:" : "lr 1/14/2010 19:22",
		"fadeToggle:" : "lr 11/13/2010 10:23",
		"fadeToggle:callback:" : "lr 11/13/2010 10:23",
		"filter:" : "lr 1/14/2010 19:23",
		"find:" : "lr 1/14/2010 19:23",
		"first" : "lr 1/14/2010 19:23",
		"get" : "lr 1/14/2010 19:25",
		"get:" : "lr 1/14/2010 19:25",
		"has:" : "lr 1/14/2010 19:26",
		"hasClass:" : "lr 1/14/2010 19:25",
		"height" : "lr 1/14/2010 19:26",
		"height:" : "lr 1/14/2010 19:26",
		"hide" : "lr 1/14/2010 19:27",
		"hide:" : "lr 1/14/2010 19:28",
		"hide:callback:" : "lr 1/14/2010 19:28",
		"hover:out:" : "lr 1/14/2010 19:28",
		"html" : "lr 1/14/2010 19:28",
		"html:" : "lr 1/14/2010 19:28",
		"id:" : "lr 10/26/2008 16:14",
		"index" : "lr 4/22/2010 14:49",
		"index:" : "lr 1/14/2010 19:28",
		"innerHeight" : "lr 1/14/2010 19:29",
		"innerWidth" : "lr 1/14/2010 19:29",
		"insertAfter:" : "lr 1/14/2010 19:29",
		"insertBefore:" : "lr 1/14/2010 19:29",
		"is:" : "lr 1/14/2010 19:29",
		"iteratorFor:return:" : "jf 12/31/2009 11:15",
		"javascriptContentOn:" : "lr 12/24/2009 10:16",
		"last" : "lr 1/14/2010 19:30",
		"length" : "lr 1/14/2010 19:30",
		"load" : "lr 1/14/2010 19:32",
		"map:" : "lr 1/14/2010 19:33",
		"next" : "lr 1/14/2010 19:34",
		"next:" : "lr 1/14/2010 19:34",
		"nextAll" : "lr 1/14/2010 19:34",
		"nextAll:" : "lr 1/14/2010 19:34",
		"nextUntil:" : "lr 1/14/2010 19:35",
		"not:" : "lr 1/14/2010 19:35",
		"off:" : "lr 11/4/2011 20:51",
		"off:selector:" : "lr 11/4/2011 20:52",
		"offset" : "lr 1/14/2010 19:36",
		"offsetLeft" : "lr 9/22/2009 09:43",
		"offsetParent" : "lr 1/14/2010 19:36",
		"offsetTop" : "lr 9/22/2009 09:43",
		"on:do:" : "lr 11/4/2011 20:48",
		"on:selector:do:" : "lr 11/4/2011 20:52",
		"onAjaxComplete:" : "lr 1/14/2010 19:09",
		"onAjaxError:" : "lr 1/14/2010 19:09",
		"onAjaxSend:" : "lr 1/14/2010 19:09",
		"onAjaxStart:" : "lr 1/14/2010 19:09",
		"onAjaxStop:" : "lr 1/14/2010 19:10",
		"onAjaxSuccess:" : "lr 1/14/2010 19:10",
		"onBlur:" : "lr 1/14/2010 19:13",
		"onChange:" : "lr 1/14/2010 19:14",
		"onClick:" : "lr 1/14/2010 19:16",
		"onDoubleClick:" : "lr 1/14/2010 19:18",
		"onError:" : "lr 1/14/2010 19:22",
		"onFocus:" : "lr 1/14/2010 19:24",
		"onFocusIn:" : "lr 1/14/2010 19:24",
		"onFocusOut:" : "lr 1/14/2010 19:24",
		"onKeyDown:" : "lr 1/14/2010 19:30",
		"onKeyPress:" : "lr 1/14/2010 19:30",
		"onKeyUp:" : "lr 1/14/2010 19:30",
		"onLoad:" : "lr 1/14/2010 19:32",
		"onMouseDown:" : "lr 1/14/2010 19:33",
		"onMouseEnter:" : "lr 1/14/2010 19:33",
		"onMouseLeave:" : "lr 1/14/2010 19:33",
		"onMouseMove:" : "lr 1/14/2010 19:33",
		"onMouseOut:" : "lr 1/14/2010 19:34",
		"onMouseOver:" : "lr 1/14/2010 19:34",
		"onMouseUp:" : "lr 1/14/2010 19:34",
		"onResize:" : "lr 1/14/2010 19:41",
		"onScroll:" : "lr 1/14/2010 19:41",
		"onSelect:" : "lr 1/14/2010 19:42",
		"onSubmit:" : "lr 1/14/2010 19:44",
		"onUnload:" : "lr 10/15/2008 16:27",
		"one:do:" : "lr 1/14/2010 19:37",
		"outerHeight" : "lr 1/14/2010 19:37",
		"outerWidth" : "lr 1/14/2010 19:37",
		"parent" : "lr 10/15/2008 16:28",
		"parent:" : "lr 10/15/2008 16:28",
		"parents" : "lr 1/14/2010 19:37",
		"parents:" : "lr 1/14/2010 19:37",
		"parentsUntil:" : "lr 1/14/2010 19:38",
		"position" : "lr 1/14/2010 19:39",
		"positionLeft" : "lr 9/22/2009 09:43",
		"positionTop" : "lr 9/22/2009 09:45",
		"prepend:" : "lr 1/14/2010 19:39",
		"prependTo:" : "lr 1/14/2010 19:39",
		"previous" : "lr 1/14/2010 19:39",
		"previous:" : "lr 1/14/2010 19:39",
		"previousAll" : "lr 1/14/2010 19:39",
		"previousAll:" : "lr 1/14/2010 19:39",
		"previousUntil:" : "lr 1/14/2010 19:39",
		"properties:" : "lr 6/3/2011 11:23",
		"propertyAt:" : "lr 6/3/2011 11:22",
		"propertyAt:put:" : "lr 6/3/2011 11:23",
		"queue" : "lr 1/14/2010 19:40",
		"queue:" : "lr 1/14/2010 19:40",
		"queue:do:" : "lr 1/14/2010 21:36",
		"remove" : "lr 1/14/2010 19:40",
		"remove:" : "lr 1/14/2010 19:40",
		"removeAttribute:" : "lr 1/14/2010 19:40",
		"removeClass:" : "lr 1/14/2010 19:40",
		"removeDataAt:" : "lr 1/14/2010 19:41",
		"removeProperty:" : "lr 6/3/2011 11:23",
		"replaceAll:" : "lr 1/14/2010 19:41",
		"replaceWith:" : "lr 1/14/2010 19:41",
		"scrollLeft" : "lr 1/14/2010 19:42",
		"scrollLeft:" : "lr 1/14/2010 19:42",
		"scrollTop" : "lr 1/14/2010 19:42",
		"scrollTop:" : "lr 1/14/2010 19:42",
		"serialize" : "lr 1/14/2010 19:42",
		"serializeArray" : "lr 1/14/2010 19:42",
		"setArguments:" : "lr 10/26/2008 16:17",
		"show" : "lr 1/14/2010 19:42",
		"show:" : "lr 1/14/2010 19:42",
		"show:callback:" : "lr 1/14/2010 19:43",
		"siblings" : "lr 1/14/2010 19:43",
		"siblings:" : "lr 1/14/2010 19:43",
		"size" : "lr 1/14/2010 19:43",
		"sliceFrom:" : "lr 1/14/2010 19:43",
		"sliceFrom:to:" : "lr 1/14/2010 19:43",
		"slideDown:" : "lr 1/14/2010 19:43",
		"slideDown:callback:" : "lr 1/14/2010 19:44",
		"slideToggle:" : "lr 1/14/2010 19:44",
		"slideToggle:callback:" : "lr 1/14/2010 19:44",
		"slideUp:" : "lr 1/14/2010 19:44",
		"slideUp:callback:" : "lr 1/14/2010 19:44",
		"stop" : "lr 1/14/2010 19:44",
		"text" : "lr 1/14/2010 19:44",
		"text:" : "lr 1/14/2010 19:45",
		"toArray" : "lr 1/14/2010 19:45",
		"toggle" : "lr 1/14/2010 19:45",
		"toggle:" : "JohanBrichau 2/25/2014 00:00",
		"toggle:callback:" : "lr 1/14/2010 19:45",
		"toggleClass:" : "lr 1/14/2010 19:46",
		"toggleClass:state:" : "lr 1/14/2009 22:21",
		"trigger:" : "lr 1/14/2010 19:46",
		"triggerBlur" : "lr 4/24/2009 20:30",
		"triggerChange" : "lr 4/24/2009 20:30",
		"triggerClick" : "lr 4/24/2009 20:30",
		"triggerDoubleClick" : "lr 4/24/2009 20:30",
		"triggerError" : "lr 4/24/2009 20:31",
		"triggerFocus" : "lr 4/24/2009 20:31",
		"triggerHandler:" : "lr 1/14/2010 19:46",
		"triggerKeyDown" : "lr 4/24/2009 20:32",
		"triggerKeyPress" : "lr 4/24/2009 20:32",
		"triggerKeyUp" : "lr 4/24/2009 20:32",
		"triggerSelect" : "lr 4/24/2009 20:32",
		"triggerSubmit" : "lr 4/24/2009 20:33",
		"unbind:" : "lr 1/14/2010 19:46",
		"undelegate" : "lr 2/20/2010 18:11",
		"undelegate:on:" : "lr 2/20/2010 18:11",
		"unwrap" : "lr 1/14/2010 19:48",
		"value" : "lr 1/14/2010 19:48",
		"value:" : "lr 1/14/2010 19:49",
		"width" : "lr 1/14/2010 19:49",
		"width:" : "lr 1/14/2010 19:49",
		"wrap:" : "lr 1/14/2010 19:49",
		"wrapAll:" : "lr 1/14/2010 19:49",
		"wrapInner:" : "lr 1/14/2010 19:49" } }
